cook_inlet_catalogs/__init__.py
cook_inlet_catalogs/_version.py
cook_inlet_catalogs/generate_catalogs.py
cook_inlet_catalogs/utils.py
cook_inlet_catalogs/catalogs/adcp_moored_noaa_coi_2005.yaml
cook_inlet_catalogs/catalogs/adcp_moored_noaa_coi_other.yaml
cook_inlet_catalogs/catalogs/adcp_moored_noaa_kod_1.yaml
cook_inlet_catalogs/catalogs/adcp_moored_noaa_kod_2.yaml
cook_inlet_catalogs/catalogs/ctd_profiles_2005_noaa.yaml
cook_inlet_catalogs/catalogs/ctd_profiles_ecofoci.yaml
cook_inlet_catalogs/catalogs/ctd_profiles_emap_2002.yaml
cook_inlet_catalogs/catalogs/ctd_profiles_emap_2008.yaml
cook_inlet_catalogs/catalogs/ctd_profiles_kachemack_kuletz_2005_2007.yaml
cook_inlet_catalogs/catalogs/ctd_profiles_kb_small_mesh_2006.yaml
cook_inlet_catalogs/catalogs/ctd_profiles_kbay_osu_2007.yaml
cook_inlet_catalogs/catalogs/ctd_profiles_piatt_speckman_1999.yaml
cook_inlet_catalogs/catalogs/ctd_profiles_usgs_boem.yaml
cook_inlet_catalogs/catalogs/ctd_towed_ferry_noaa_pmel.yaml
cook_inlet_catalogs/catalogs/ctd_towed_gwa.yaml
cook_inlet_catalogs/catalogs/ctd_towed_gwa_temp.yaml
cook_inlet_catalogs/catalogs/ctd_towed_otf_kbnerr.yaml
cook_inlet_catalogs/catalogs/ctd_transects_barabara_to_bluff_2002_2003.yaml
cook_inlet_catalogs/catalogs/ctd_transects_cmi_kbnerr.yaml
cook_inlet_catalogs/catalogs/ctd_transects_cmi_uaf.yaml
cook_inlet_catalogs/catalogs/ctd_transects_gwa.yaml
cook_inlet_catalogs/catalogs/ctd_transects_misc_2002.yaml
cook_inlet_catalogs/catalogs/ctd_transects_otf_kbnerr.yaml
cook_inlet_catalogs/catalogs/ctd_transects_uaf.yaml
cook_inlet_catalogs/catalogs/drifters_ecofoci.yaml
cook_inlet_catalogs/catalogs/drifters_epscor.yaml
cook_inlet_catalogs/catalogs/drifters_lake_clark.yaml
cook_inlet_catalogs/catalogs/drifters_uaf.yaml
cook_inlet_catalogs/catalogs/hfradar.yaml
cook_inlet_catalogs/catalogs/moorings_aoos_cdip.yaml
cook_inlet_catalogs/catalogs/moorings_circac.yaml
cook_inlet_catalogs/catalogs/moorings_kbnerr.yaml
cook_inlet_catalogs-1.1.dist-info/licenses/LICENSE.txt
cook_inlet_catalogs-1.1.dist-info/METADATA
cook_inlet_catalogs-1.1.dist-info/WHEEL
cook_inlet_catalogs-1.1.dist-info/top_level.txt
cook_inlet_catalogs-1.1.dist-info/RECORD
