Metadata-Version: 2.4
Name: cook_inlet_catalogs
Version: 1.1
Summary: Intake catalogs of datasets from Cook Inlet, AK
Home-page: https://github.com/axiom-data-science/cook-inlet-catalogs
Author: axiom-data-science
Author-email: kristen@axds.co
License: MIT
Classifier: Development Status :: 5 - Production/Stable
Classifier: Topic :: Scientific/Engineering
Classifier: Intended Audience :: Science/Research
Classifier: Operating System :: OS Independent
Classifier: Programming Language :: Python
Classifier: Programming Language :: Python :: 3
Classifier: Programming Language :: Python :: 3.9
Classifier: Programming Language :: Python :: 3.10
Classifier: Programming Language :: Python :: 3.11
Classifier: License :: OSI Approved :: MIT License
Requires-Python: >=3.8
License-File: LICENSE.txt
Requires-Dist: aiohttp
Requires-Dist: appdirs
Requires-Dist: cartopy
Requires-Dist: cf_pandas
Requires-Dist: cf_xarray
Requires-Dist: cmocean
Requires-Dist: geoviews
Requires-Dist: h5netcdf
Requires-Dist: hvplot
Requires-Dist: jupyter
Requires-Dist: jupyter_bokeh
Requires-Dist: matplotlib
Requires-Dist: numpy
Requires-Dist: openpyxl
Requires-Dist: pandas
Requires-Dist: pip
Requires-Dist: pyproj
Requires-Dist: requests
Dynamic: license-file
